thorondor/README.md
thorondor/__init__.py
thorondor/gui.py
thorondor/gui_iterable.py
thorondor/Elements/00README.txt
thorondor/Elements/He.txt
thorondor/Elements/O.txt
thorondor/Elements/ac.nff
thorondor/Elements/ag.nff
thorondor/Elements/al.nff
thorondor/Elements/ar.nff
thorondor/Elements/as.nff
thorondor/Elements/at.nff
thorondor/Elements/au.nff
thorondor/Elements/b.nff
thorondor/Elements/ba.nff
thorondor/Elements/be.nff
thorondor/Elements/bi.nff
thorondor/Elements/br.nff
thorondor/Elements/c.nff
thorondor/Elements/ca.nff
thorondor/Elements/cd.nff
thorondor/Elements/ce.nff
thorondor/Elements/cl.nff
thorondor/Elements/co.nff
thorondor/Elements/cr.nff
thorondor/Elements/cs.nff
thorondor/Elements/cu.nff
thorondor/Elements/dy.nff
thorondor/Elements/er.nff
thorondor/Elements/eu.nff
thorondor/Elements/f.nff
thorondor/Elements/fe.nff
thorondor/Elements/fr.nff
thorondor/Elements/ga.nff
thorondor/Elements/gd.nff
thorondor/Elements/ge.nff
thorondor/Elements/h.nff
thorondor/Elements/he.nff
thorondor/Elements/hf.nff
thorondor/Elements/hg.nff
thorondor/Elements/ho.nff
thorondor/Elements/i.nff
thorondor/Elements/in.nff
thorondor/Elements/ir.nff
thorondor/Elements/k.nff
thorondor/Elements/kr.nff
thorondor/Elements/la.nff
thorondor/Elements/li.nff
thorondor/Elements/lu.nff
thorondor/Elements/membrane.txt
thorondor/Elements/mg.nff
thorondor/Elements/mn.nff
thorondor/Elements/mo.nff
thorondor/Elements/n.nff
thorondor/Elements/na.nff
thorondor/Elements/nb.nff
thorondor/Elements/nd.nff
thorondor/Elements/ne.nff
thorondor/Elements/ni.nff
thorondor/Elements/o.nff
thorondor/Elements/os.nff
thorondor/Elements/p.nff
thorondor/Elements/pa.nff
thorondor/Elements/pb.nff
thorondor/Elements/pd.nff
thorondor/Elements/pm.nff
thorondor/Elements/po.nff
thorondor/Elements/pr.nff
thorondor/Elements/pt.nff
thorondor/Elements/ra.nff
thorondor/Elements/rb.nff
thorondor/Elements/re.nff
thorondor/Elements/rh.nff
thorondor/Elements/rn.nff
thorondor/Elements/ru.nff
thorondor/Elements/s.nff
thorondor-0.3.30.dist-info/METADATA
thorondor-0.3.30.dist-info/WHEEL
thorondor-0.3.30.dist-info/licence.txt
thorondor-0.3.30.dist-info/top_level.txt
thorondor-0.3.30.dist-info/RECORD
