Metadata-Version: 2.1
Name: thorondor
Version: 0.3.30
Summary: XANES package using jupyter widgets
Home-page: https://pypi.org/project/thorondor/
Author: David Simonne and Andrea Martini
Author-email: david.simonne@synchrotron-soleil.fr, andrea.martini@unito.it
License: UNKNOWN
Keywords: XANES GUI lmfit widgets
Platform: UNKNOWN
Classifier: Programming Language :: Python :: 3
Classifier: License :: OSI Approved :: GNU General Public License v3 (GPLv3)
Classifier: Operating System :: OS Independent
Requires-Python: >=3.6
Requires-Dist: numpy
Requires-Dist: pandas
Requires-Dist: matplotlib
Requires-Dist: ipywidgets
Requires-Dist: ipython
Requires-Dist: scipy
Requires-Dist: lmfit
Requires-Dist: emcee
Requires-Dist: corner
Requires-Dist: xlrd
Requires-Dist: numdifftools
Requires-Dist: tables
